{
  "generatedAt": "2026-06-07T08:45:39.638Z",
  "baseUrl": "https://townpet.vercel.app",
  "sampleCount": 3,
  "settleMs": 3500,
  "profiles": [
    "desktop",
    "mobile"
  ],
  "targets": [
    {
      "label": "home",
      "path": "/"
    },
    {
      "label": "guest_feed",
      "path": "/feed/guest"
    }
  ],
  "summaries": [
    {
      "profile": "desktop",
      "label": "guest_feed",
      "path": "/feed/guest",
      "count": 3,
      "statusSummary": "200x3",
      "responseEndP50": 129.09999999403954,
      "fcpP50": 196,
      "fcpP95": 196,
      "lcpP50": 196,
      "lcpP95": 196,
      "loadP50": 196.5,
      "loadP95": 240.90000000596046,
      "totalGotoP50": 197.91033400000015,
      "totalGotoP95": 241.9540419999994
    },
    {
      "profile": "desktop",
      "label": "home",
      "path": "/",
      "count": 3,
      "statusSummary": "200x3",
      "responseEndP50": 128.80000001192093,
      "fcpP50": 208,
      "fcpP95": 260,
      "lcpP50": 208,
      "lcpP95": 260,
      "loadP50": 212.69999998807907,
      "loadP95": 262.59999999403954,
      "totalGotoP50": 213.68912499999988,
      "totalGotoP95": 267.5009580000001
    },
    {
      "profile": "mobile",
      "label": "guest_feed",
      "path": "/feed/guest",
      "count": 3,
      "statusSummary": "200x3",
      "responseEndP50": 127.7999999821186,
      "fcpP50": 176,
      "fcpP95": 180,
      "lcpP50": 176,
      "lcpP95": 180,
      "loadP50": 206.89999997615814,
      "loadP95": 208.60000002384186,
      "totalGotoP50": 207.66908300000068,
      "totalGotoP95": 209.9921250000043
    },
    {
      "profile": "mobile",
      "label": "home",
      "path": "/",
      "count": 3,
      "statusSummary": "200x3",
      "responseEndP50": 135.09999999403954,
      "fcpP50": 188,
      "fcpP95": 212,
      "lcpP50": 188,
      "lcpP95": 212,
      "loadP50": 195.2999999821186,
      "loadP95": 218.19999998807907,
      "totalGotoP50": 196.56737499999872,
      "totalGotoP95": 219.48454100000163
    }
  ],
  "samples": [
    {
      "profile": "desktop",
      "label": "home",
      "path": "/",
      "index": 1,
      "status": 200,
      "finalUrl": "https://townpet.vercel.app/",
      "responseEndMs": 168.7000000178814,
      "domContentLoadedMs": 227,
      "loadEventMs": 262.59999999403954,
      "firstPaintMs": 260,
      "fcpMs": 260,
      "lcpMs": 260,
      "totalGotoMs": 267.5009580000001,
      "bodyTextLength": 1157
    },
    {
      "profile": "desktop",
      "label": "home",
      "path": "/",
      "index": 2,
      "status": 200,
      "finalUrl": "https://townpet.vercel.app/",
      "responseEndMs": 128.69999998807907,
      "domContentLoadedMs": 175.2999999821186,
      "loadEventMs": 212.69999998807907,
      "firstPaintMs": 200,
      "fcpMs": 200,
      "lcpMs": 200,
      "totalGotoMs": 213.68912499999988,
      "bodyTextLength": 1157
    },
    {
      "profile": "desktop",
      "label": "home",
      "path": "/",
      "index": 3,
      "status": 200,
      "finalUrl": "https://townpet.vercel.app/",
      "responseEndMs": 128.80000001192093,
      "domContentLoadedMs": 202.59999999403954,
      "loadEventMs": 202.59999999403954,
      "firstPaintMs": 208,
      "fcpMs": 208,
      "lcpMs": 208,
      "totalGotoMs": 204.0269159999989,
      "bodyTextLength": 1157
    },
    {
      "profile": "desktop",
      "label": "guest_feed",
      "path": "/feed/guest",
      "index": 1,
      "status": 200,
      "finalUrl": "https://townpet.vercel.app/feed/guest",
      "responseEndMs": 129.09999999403954,
      "domContentLoadedMs": 177.90000000596046,
      "loadEventMs": 240.90000000596046,
      "firstPaintMs": 196,
      "fcpMs": 196,
      "lcpMs": 196,
      "totalGotoMs": 241.9540419999994,
      "bodyTextLength": 1618
    },
    {
      "profile": "desktop",
      "label": "guest_feed",
      "path": "/feed/guest",
      "index": 2,
      "status": 200,
      "finalUrl": "https://townpet.vercel.app/feed/guest",
      "responseEndMs": 126.40000000596046,
      "domContentLoadedMs": 193.60000002384186,
      "loadEventMs": 193.60000002384186,
      "firstPaintMs": 192,
      "fcpMs": 192,
      "lcpMs": 192,
      "totalGotoMs": 194.96195799999987,
      "bodyTextLength": 1618
    },
    {
      "profile": "desktop",
      "label": "guest_feed",
      "path": "/feed/guest",
      "index": 3,
      "status": 200,
      "finalUrl": "https://townpet.vercel.app/feed/guest",
      "responseEndMs": 132.2999999821186,
      "domContentLoadedMs": 196.39999997615814,
      "loadEventMs": 196.5,
      "firstPaintMs": 196,
      "fcpMs": 196,
      "lcpMs": 196,
      "totalGotoMs": 197.91033400000015,
      "bodyTextLength": 1618
    },
    {
      "profile": "mobile",
      "label": "home",
      "path": "/",
      "index": 1,
      "status": 200,
      "finalUrl": "https://townpet.vercel.app/",
      "responseEndMs": 137.90000000596046,
      "domContentLoadedMs": 218.19999998807907,
      "loadEventMs": 218.19999998807907,
      "firstPaintMs": 212,
      "fcpMs": 212,
      "lcpMs": 212,
      "totalGotoMs": 219.48454100000163,
      "bodyTextLength": 1721
    },
    {
      "profile": "mobile",
      "label": "home",
      "path": "/",
      "index": 2,
      "status": 200,
      "finalUrl": "https://townpet.vercel.app/",
      "responseEndMs": 131.39999997615814,
      "domContentLoadedMs": 195.2999999821186,
      "loadEventMs": 195.2999999821186,
      "firstPaintMs": 184,
      "fcpMs": 184,
      "lcpMs": 184,
      "totalGotoMs": 196.56737499999872,
      "bodyTextLength": 1721
    },
    {
      "profile": "mobile",
      "label": "home",
      "path": "/",
      "index": 3,
      "status": 200,
      "finalUrl": "https://townpet.vercel.app/",
      "responseEndMs": 135.09999999403954,
      "domContentLoadedMs": 193.69999998807907,
      "loadEventMs": 193.69999998807907,
      "firstPaintMs": 188,
      "fcpMs": 188,
      "lcpMs": 188,
      "totalGotoMs": 194.7532089999986,
      "bodyTextLength": 1721
    },
    {
      "profile": "mobile",
      "label": "guest_feed",
      "path": "/feed/guest",
      "index": 1,
      "status": 200,
      "finalUrl": "https://townpet.vercel.app/feed/guest",
      "responseEndMs": 126.10000002384186,
      "domContentLoadedMs": 169.30000001192093,
      "loadEventMs": 208.60000002384186,
      "firstPaintMs": 176,
      "fcpMs": 176,
      "lcpMs": 176,
      "totalGotoMs": 209.9921250000043,
      "bodyTextLength": 1239
    },
    {
      "profile": "mobile",
      "label": "guest_feed",
      "path": "/feed/guest",
      "index": 2,
      "status": 200,
      "finalUrl": "https://townpet.vercel.app/feed/guest",
      "responseEndMs": 131.5,
      "domContentLoadedMs": 173.90000000596046,
      "loadEventMs": 195.19999998807907,
      "firstPaintMs": 180,
      "fcpMs": 180,
      "lcpMs": 180,
      "totalGotoMs": 196.39529100000073,
      "bodyTextLength": 1239
    },
    {
      "profile": "mobile",
      "label": "guest_feed",
      "path": "/feed/guest",
      "index": 3,
      "status": 200,
      "finalUrl": "https://townpet.vercel.app/feed/guest",
      "responseEndMs": 127.7999999821186,
      "domContentLoadedMs": 169.2999999821186,
      "loadEventMs": 206.89999997615814,
      "firstPaintMs": 176,
      "fcpMs": 176,
      "lcpMs": 176,
      "totalGotoMs": 207.66908300000068,
      "bodyTextLength": 1239
    }
  ]
}
